amdata/__init__.py
amdata/db.py
amdata-0.1.2.dist-info/licenses/LICENSE
amdata-0.1.2.dist-info/METADATA
amdata-0.1.2.dist-info/WHEEL
amdata-0.1.2.dist-info/top_level.txt
amdata-0.1.2.dist-info/RECORD
