Metadata-Version: 2.4
Name: amdata
Version: 0.1.2
Summary: A simple and easy-to-use library to manage SQLite databases.
Home-page: https://github.com/HACKER-AMJAD
Author: Amjad
Author-email: amjadchoufi@gmail.com
Classifier: Programming Language :: Python :: 3
Classifier: License :: OSI Approved :: GNU General Public License v3 (GPLv3)
Classifier: Operating System :: OS Independent
Requires-Python: >=3.6
License-File: LICENSE
Dynamic: author
Dynamic: author-email
Dynamic: classifier
Dynamic: description
Dynamic: description-content-type
Dynamic: home-page
Dynamic: license-file
Dynamic: requires-python
Dynamic: summary
